aiogramic/__init__.py
aiogramic/__main__.py
aiogramic/commands/__init__.py
aiogramic/commands/create_callback_data.py
aiogramic/commands/create_filter.py
aiogramic/commands/create_handler.py
aiogramic/commands/create_inline_keyboard.py
aiogramic/commands/create_keyboard.py
aiogramic/commands/create_middleware.py
aiogramic/commands/create_state.py
aiogramic/commands/init_app.py
aiogramic/enums/__init__.py
aiogramic/enums/entity_type.py
aiogramic/enums/handler_type.py
aiogramic/templates/app/.env.example
aiogramic/templates/app/.gitignore
aiogramic/templates/app/README.md
aiogramic/templates/app/src/__init__.py
aiogramic/templates/app/src/__main__.py
aiogramic/templates/app/src/cfg.py
aiogramic/templates/app/src/handlers/__init__.py
aiogramic/templates/app/src/handlers/command/__init__.py
aiogramic/templates/app/src/handlers/command/router.py
aiogramic/templates/app/src/handlers/command/start_command.py
aiogramic/templates/app/src/handlers/router.py
aiogramic/templates/app/tests/conftest.py
aiogramic/templates/callback_data
aiogramic/templates/docker/Dockerfile
aiogramic/templates/docker/docker-compose.yaml
aiogramic/templates/handlers/callback_query_handler
aiogramic/templates/handlers/channel_post_handler
aiogramic/templates/handlers/chat_member_handler
aiogramic/templates/handlers/command_handler
aiogramic/templates/handlers/edited_message_handler
aiogramic/templates/handlers/message_handler
aiogramic/templates/handlers/my_chat_member_handler
aiogramic/templates/keyboards/inline
aiogramic/templates/keyboards/text
aiogramic/templates/middleware
aiogramic/utils/builders.py
aiogramic/utils/create_handler.py
aiogramic/utils/file.py
aiogramic-0.2.0.dist-info/METADATA
aiogramic-0.2.0.dist-info/WHEEL
aiogramic-0.2.0.dist-info/RECORD
